odoo9_addon_purchase_discount-9.0.1.1.1-py2.7-nspkg.pth
odoo9_addon_purchase_discount-9.0.1.1.1.dist-info/METADATA
odoo9_addon_purchase_discount-9.0.1.1.1.dist-info/RECORD
odoo9_addon_purchase_discount-9.0.1.1.1.dist-info/WHEEL
odoo9_addon_purchase_discount-9.0.1.1.1.dist-info/namespace_packages.txt
odoo9_addon_purchase_discount-9.0.1.1.1.dist-info/top_level.txt
odoo_addons/purchase_discount/README.rst
odoo_addons/purchase_discount/__init__.py
odoo_addons/purchase_discount/__openerp__.py
odoo_addons/purchase_discount/i18n/ca.po
odoo_addons/purchase_discount/i18n/de.po
odoo_addons/purchase_discount/i18n/el_GR.po
odoo_addons/purchase_discount/i18n/es.po
odoo_addons/purchase_discount/i18n/es_MX.po
odoo_addons/purchase_discount/i18n/es_PE.po
odoo_addons/purchase_discount/i18n/fi.po
odoo_addons/purchase_discount/i18n/fr.po
odoo_addons/purchase_discount/i18n/fr_CH.po
odoo_addons/purchase_discount/i18n/fr_FR.po
odoo_addons/purchase_discount/i18n/gl.po
odoo_addons/purchase_discount/i18n/hr.po
odoo_addons/purchase_discount/i18n/it.po
odoo_addons/purchase_discount/i18n/nl.po
odoo_addons/purchase_discount/i18n/nl_NL.po
odoo_addons/purchase_discount/i18n/pt_BR.po
odoo_addons/purchase_discount/i18n/pt_PT.po
odoo_addons/purchase_discount/i18n/ro.po
odoo_addons/purchase_discount/i18n/ru.po
odoo_addons/purchase_discount/i18n/sl.po
odoo_addons/purchase_discount/i18n/tr.po
odoo_addons/purchase_discount/i18n/tr_TR.po
odoo_addons/purchase_discount/i18n/vi_VN.po
odoo_addons/purchase_discount/i18n/zh_CN.po
odoo_addons/purchase_discount/images/purchase_discount.png
odoo_addons/purchase_discount/models/__init__.py
odoo_addons/purchase_discount/models/account_invoice.py
odoo_addons/purchase_discount/models/purchase_order.py
odoo_addons/purchase_discount/static/description/icon.png
odoo_addons/purchase_discount/static/description/icon.svg
odoo_addons/purchase_discount/tests/__init__.py
odoo_addons/purchase_discount/tests/test_purchase_discount.py
odoo_addons/purchase_discount/views/purchase_discount_view.xml
odoo_addons/purchase_discount/views/report_purchaseorder.xml
